wordlehelper/__init__.py
wordlehelper/words.py
guesstheword-0.0.2.dist-info/LICENSE.txt
guesstheword-0.0.2.dist-info/METADATA
guesstheword-0.0.2.dist-info/WHEEL
guesstheword-0.0.2.dist-info/entry_points.txt
guesstheword-0.0.2.dist-info/top_level.txt
guesstheword-0.0.2.dist-info/RECORD
