Metadata-Version: 2.1
Name: guesstheword
Version: 0.0.2
Summary: The package targets to help user in playing the game wordle
Home-page: https://github.com/dextrop/wordlehelper
Author: ASK Jennie
Author-email: ASK Jennie Developer <saurabh@ask-jennie.com>
License: UNKNOWN
Platform: UNKNOWN
Classifier: License :: OSI Approved :: MIT License
Classifier: Programming Language :: Python :: 3
Classifier: Programming Language :: Python :: 3.7
License-File: LICENSE.txt
Requires-Dist: requests
